pod2gen/__init__.py
pod2gen/__main__.py
pod2gen/alternate_media.py
pod2gen/category.py
pod2gen/constants.py
pod2gen/episode.py
pod2gen/funding.py
pod2gen/license.py
pod2gen/location.py
pod2gen/media.py
pod2gen/person.py
pod2gen/podcast.py
pod2gen/soundbite.py
pod2gen/trailer.py
pod2gen/transcript.py
pod2gen/util.py
pod2gen/version.py
pod2gen/warnings.py
pod2gen-1.0.3.dist-info/METADATA
pod2gen-1.0.3.dist-info/WHEEL
pod2gen-1.0.3.dist-info/top_level.txt
pod2gen-1.0.3.dist-info/RECORD
