Metadata-Version: 2.1
Name: pod2gen
Version: 1.0.3
Summary: Generating podcasts with Python should be easy!
Home-page: https://pod2gen.caproni.fm/en/latest/
Author: Slim Beji
Author-email: mslimbeji@gmail.com
License: FreeBSD and LGPLv3+
Keywords: feed,RSS,podcast,iTunes,generator
Platform: UNKNOWN
Classifier: Development Status :: 5 - Production/Stable
Classifier: Intended Audience :: Developers
Classifier: Intended Audience :: Information Technology
Classifier: Intended Audience :: Science/Research
Classifier: License :: OSI Approved :: BSD License
Classifier: License :: OSI Approved :: GNU Lesser General Public License v3 or later (LGPLv3+)
Classifier: Natural Language :: English
Classifier: Operating System :: OS Independent
Classifier: Programming Language :: Python
Classifier: Programming Language :: Python :: 3
Classifier: Programming Language :: Python :: 3.6
Classifier: Programming Language :: Python :: 3.7
Classifier: Programming Language :: Python :: 3.8
Classifier: Topic :: Communications
Classifier: Topic :: Internet
Classifier: Topic :: Software Development :: Libraries :: Python Modules
Classifier: Topic :: Text Processing
Classifier: Topic :: Text Processing :: Markup
Classifier: Topic :: Text Processing :: Markup :: XML
Requires-Python: >=3.6.*
Requires-Dist: lxml
Requires-Dist: dateutils
Requires-Dist: tinytag
Requires-Dist: requests
Requires-Dist: pycountry
Requires-Dist: validators
